getsecure.py
getsecure-0.0.8.dist-info/LICENSE
getsecure-0.0.8.dist-info/METADATA
getsecure-0.0.8.dist-info/WHEEL
getsecure-0.0.8.dist-info/RECORD
