Metadata-Version: 2.1
Name: getsecure
Version: 0.0.8
Summary: Utility for securing expiring links
Home-page: https://github.com/maratsh/getsecure
License: MIT
Keywords: nginx, secure_ling
Author: maratsh
Author-email: ya@maratsh.ru
Requires-Python: >=3.7,<4.0
Classifier: License :: OSI Approved :: MIT License
Classifier: Programming Language :: Python :: 3
Classifier: Programming Language :: Python :: 3.7
Classifier: Programming Language :: Python :: 3.8
Classifier: Programming Language :: Python :: 3.9
Classifier: Programming Language :: Python :: 3.10
Classifier: Programming Language :: Python :: 3.11
Classifier: Programming Language :: Python :: 3.12
Project-URL: Repository, https://github.com/maratsh/getsecure
